{
  "atualizado": "20/06/2026 00:11",
  "total": 136,
  "ofertas": [
    {
      "title": "Caminhão Dinossauro Pista Com Carrinhos Maleta Transporte",
      "price": 82.0,
      "original_price": 400.0,
      "discount": 80,
      "permalink": "https://produto.mercadolivre.com.br/MLB-4140033567-caminho-dinossauro-pista-com-carrinhos-maleta-transporte-_JM?matt_word=birutaofertas&matt_tool=48037708",
      "categoria": "Brinquedos",
      "img": "https://http2.mlstatic.com/D_Q_NP_2X_948327-MLB104929140435_012026-O-caminho-dinossauro-pista-com-carrinhos-maleta-transporte.webp",
      "emoji": "🧸",
      "destaque": true
    },
    {
      "title": "Caminhão Dinossauro Pista Com 6 Carrinhos Maleta Transporte Azul",
      "price": 144.0,
      "original_price": 597.0,
      "discount": 76,
      "permalink": "https://www.mercadolivre.com.br/caminhao-dinossauro-pista-com-6-carrinhos-maleta-transporte/up/MLBU3766781957?matt_word=birutaofertas&matt_tool=48037708",
      "categoria": "Brinquedos",
      "img": "https://http2.mlstatic.com/D_Q_NP_2X_802771-MLB105838199600_022026-AB.webp",
      "emoji": "🧸",
      "destaque": true
    },
    {
      "title": "Creatina 1kg Suplemento Monohidratada Em Pó 100% Pura - Soldiers Nutrition Sem Sabor",
      "price": 59.0,
      "original_price": 239.0,
      "discount": 75,
      "permalink": "https://www.mercadolivre.com.br/creatina-1kg-suplemento-monohidratada-em-po-100-pura-soldiers-nutrition/p/MLB18725310?matt_word=birutaofertas&matt_tool=48037708",
      "categoria": "Ofertas do Dia",
      "img": "https://http2.mlstatic.com/D_Q_NP_2X_894230-MLA111390627295_052026-AB.webp",
      "emoji": "🔥",
      "destaque": true
    },
    {
      "title": "Álbum De Figurinhas Colecionáveis Copa Do Mundo Fifa 2026 Capa Dura",
      "price": 49.0,
      "original_price": 199.0,
      "discount": 75,
      "permalink": "https://www.mercadolivre.com.br/album-de-figurinhas-colecionaveis-copa-do-mundo-fifa-2026/up/MLBU3946202586?matt_word=birutaofertas&matt_tool=48037708",
      "categoria": "Brinquedos",
      "img": "https://http2.mlstatic.com/D_Q_NP_2X_821169-MLB110559528776_052026-AB.webp",
      "emoji": "🧸",
      "destaque": true
    },
    {
      "title": "Brinquedo Caminhão Dinossauro Que Engole Carros Con Lançado Caminhão De Engolir Dinossauro Azul",
      "price": 154.0,
      "original_price": 600.0,
      "discount": 74,
      "permalink": "https://www.mercadolivre.com.br/brinquedo-caminhao-dinossauro-que-engole-carros-con-lancado/up/MLBU3870842001?matt_word=birutaofertas&matt_tool=48037708",
      "categoria": "Brinquedos",
      "img": "https://http2.mlstatic.com/D_Q_NP_2X_826055-MLB109965189720_042026-AB.webp",
      "emoji": "🧸",
      "destaque": true
    },
    {
      "title": "Kit 6 Pares Meias Puma Cano Médio Alto Atoalhada Original",
      "price": 66.0,
      "original_price": 249.0,
      "discount": 73,
      "permalink": "https://produto.mercadolivre.com.br/MLB-3239976866-kit-6-pares-meias-puma-cano-medio-alto-atoalhada-original-_JM?matt_word=birutaofertas&matt_tool=48037708",
      "categoria": "Moda",
      "img": "https://http2.mlstatic.com/D_Q_NP_2X_617361-MLB54128842596_032023-O-kit-6-pares-meias-puma-cano-medio-alto-atoalhada-original.webp",
      "emoji": "👗",
      "destaque": true
    },
    {
      "title": "Kit 10 Cuecas Boxer Reebok Sem Costura Microfibra",
      "price": 78.0,
      "original_price": 269.0,
      "discount": 71,
      "permalink": "https://produto.mercadolivre.com.br/MLB-4592797548-kit-10-cuecas-boxer-reebok-sem-costura-microfibra-_JM?matt_word=birutaofertas&matt_tool=48037708",
      "categoria": "Ofertas do Dia",
      "img": "https://http2.mlstatic.com/D_Q_NP_2X_729685-MLB111397919667_052026-O-kit-10-cuecas-boxer-reebok-sem-costura-microfibra.webp",
      "emoji": "🔥",
      "destaque": true
    },
    {
      "title": "Álbum Copa Do Mundo 26 Dourado Ouro Oficial + 140 Figurinha",
      "price": 249.0,
      "original_price": 819.0,
      "discount": 70,
      "permalink": "https://www.mercadolivre.com.br/album-copa-do-mundo-26-dourado-ouro-oficial--140-figurinha/up/MLBU3951121111?matt_word=birutaofertas&matt_tool=48037708",
      "categoria": "Brinquedos",
      "img": "https://http2.mlstatic.com/D_Q_NP_2X_923414-MLB110550719764_052026-AB.webp",
      "emoji": "🧸",
      "destaque": true
    },
    {
      "title": "Parafusadeira Furadeira C/ 2 Baterias Maleta Kit Completo Led Eixo Flexível Vários Níveis Torque Simake Amarelo 127/220v 60 Hz",
      "price": 94.0,
      "original_price": 299.0,
      "discount": 69,
      "permalink": "https://www.mercadolivre.com.br/parafusadeira-furadeira-c-2-baterias-maleta-kit-completo-led-eixo-flexivel-varios-niveis-torque-simake/p/MLB50181290?matt_word=birutaofertas&matt_tool=48037708",
      "categoria": "Ofertas do Dia",
      "img": "https://http2.mlstatic.com/D_Q_NP_2X_641541-MLA111608975062_062026-AB.webp",
      "emoji": "🔥",
      "destaque": true
    },
    {
      "title": "Cooktop De Indução 1 Boca Preto Com Trava De Segurança Painel Touch Screen 127v",
      "price": 99.0,
      "original_price": 299.0,
      "discount": 67,
      "permalink": "https://www.mercadolivre.com.br/cooktop-de-induco-1-boca-preto-com-trava-de-seguranca-painel-touch-screen/p/MLB41541009?matt_word=birutaofertas&matt_tool=48037708",
      "categoria": "Ofertas do Dia",
      "img": "https://http2.mlstatic.com/D_Q_NP_2X_962538-MLA99502467392_112025-AB.webp",
      "emoji": "🔥",
      "destaque": true
    },
    {
      "title": "Creatina Monohidratada Pura 500g Dark Lab Unidade Sem Sabor",
      "price": 44.0,
      "original_price": 129.0,
      "discount": 66,
      "permalink": "https://www.mercadolivre.com.br/creatina-monohidratada-pura-500g-dark-lab-unidade/p/MLB26796581?matt_word=birutaofertas&matt_tool=48037708",
      "categoria": "Esportes",
      "img": "https://http2.mlstatic.com/D_Q_NP_2X_942122-MLA99923169249_112025-AB.webp",
      "emoji": "⚽",
      "destaque": true
    },
    {
      "title": "Cama Elástica Pula Pula Infantil Trampolim 1,4 Metros Atentu",
      "price": 226.0,
      "original_price": 659.0,
      "discount": 66,
      "permalink": "https://www.mercadolivre.com.br/cama-elastica-pula-pula-infantil-trampolim-14-metros-atentu/p/MLB28717101?matt_word=birutaofertas&matt_tool=48037708",
      "categoria": "Brinquedos",
      "img": "https://http2.mlstatic.com/D_Q_NP_2X_917104-MLA96155675715_102025-AB.webp",
      "emoji": "🧸",
      "destaque": true
    },
    {
      "title": "Cadeira De Escritório Oficial Webshop Diretor Mesh Dir360 Ergonômica Preta Com Estofado De Malha Preto",
      "price": 102.0,
      "original_price": 288.0,
      "discount": 65,
      "permalink": "https://www.mercadolivre.com.br/cadeira-de-escritorio-oficial-webshop-diretor-mesh-dir360-ergonmica-preta-com-estofado-de-malha/p/MLB27437738?matt_word=birutaofertas&matt_tool=48037708",
      "categoria": "Eletrodomésticos",
      "img": "https://http2.mlstatic.com/D_Q_NP_2X_640673-MLA107743768573_022026-AB.webp",
      "emoji": "🏠",
      "destaque": true
    },
    {
      "title": "Polares Z20pro Patinete Elétrico Premium 500w Pneu Aderente Velocidade Máxima 32km/h Motorizado Até 30km De Autonomia Polares Cor Preto Slin",
      "price": 1745.0,
      "original_price": 4999.0,
      "discount": 65,
      "permalink": "https://www.mercadolivre.com.br/polares-z20pro-patinete-eletrico-premium-500w-pneu-aderente-velocidade-maxima-32kmh-motorizado-ate-30km-de-autonomia-polares-cor-preto/p/MLB54490025?matt_word=birutaofertas&matt_tool=48037708",
      "categoria": "Brinquedos",
      "img": "https://http2.mlstatic.com/D_Q_NP_2X_906929-MLA111087038387_042026-AB.webp",
      "emoji": "🧸",
      "destaque": true
    },
    {
      "title": "Tênis New Balance Fresh Foam Arishiv4 Masculino Original",
      "price": 233.0,
      "original_price": 639.0,
      "discount": 64,
      "permalink": "https://produto.mercadolivre.com.br/MLB-5547123710-tnis-new-balance-fresh-foam-arishiv4-masculino-original-_JM?matt_word=birutaofertas&matt_tool=48037708",
      "categoria": "Ofertas do Dia",
      "img": "https://http2.mlstatic.com/D_Q_NP_2X_936344-MLB89212091538_082025-O-tnis-new-balance-fresh-foam-arishiv4-masculino-original.webp",
      "emoji": "🔥",
      "destaque": true
    },
    {
      "title": "Capa Protetora Colchão Box Casal Padrão Matelado Impermeável",
      "price": 28.0,
      "original_price": 78.0,
      "discount": 64,
      "permalink": "https://produto.mercadolivre.com.br/MLB-4002919471-capa-protetora-colcho-box-casal-padro-matelado-impermeavel-_JM?matt_word=birutaofertas&matt_tool=48037708",
      "categoria": "Eletrodomésticos",
      "img": "https://http2.mlstatic.com/D_Q_NP_2X_639258-MLB82839590542_032025-O-capa-protetora-colcho-box-casal-padro-matelado-impermeavel.webp",
      "emoji": "🏠",
      "destaque": true
    },
    {
      "title": "Camiseta Light T-shirt Insider Masculino",
      "price": 69.0,
      "original_price": 189.0,
      "discount": 63,
      "permalink": "https://produto.mercadolivre.com.br/MLB-4085597457-camiseta-light-t-shirt-insider-masculino-_JM?matt_word=birutaofertas&matt_tool=48037708",
      "categoria": "Moda",
      "img": "https://http2.mlstatic.com/D_Q_NP_2X_779849-MLB89746747076_082025-O-camiseta-light-t-shirt-insider-masculino.webp",
      "emoji": "👗",
      "destaque": true
    },
    {
      "title": "Monitor Viewpro Mwv21 Led De 21.5  Full Hd Com Hdmi E Vga Preto 127/220v",
      "price": 265.0,
      "original_price": 699.0,
      "discount": 62,
      "permalink": "https://www.mercadolivre.com.br/monitor-viewpro-mwv21-led-de-215-full-hd-com-hdmi-e-vga/p/MLB51873735?matt_word=birutaofertas&matt_tool=48037708",
      "categoria": "Informática",
      "img": "https://http2.mlstatic.com/D_Q_NP_2X_987156-MLA99990528997_112025-AB.webp",
      "emoji": "💻",
      "destaque": true
    },
    {
      "title": "Projetor Portátil 4k Hd Android 11.0 Smart Wifi 5g Bluetooth Branco 127/220v",
      "price": 256.0,
      "original_price": 679.0,
      "discount": 62,
      "permalink": "https://www.mercadolivre.com.br/projetor-portatil-4k-hd-android-110-smart-wifi-5g-bluetooth/up/MLBU4002345613?matt_word=birutaofertas&matt_tool=48037708",
      "categoria": "Informática",
      "img": "https://http2.mlstatic.com/D_Q_NP_2X_724460-MLB112257160959_052026-AB.webp",
      "emoji": "💻",
      "destaque": true
    },
    {
      "title": "Meia Calça De Lã Térmica Translúcida Pelúcia Forrada Pelinho",
      "price": 27.0,
      "original_price": 69.0,
      "discount": 61,
      "permalink": "https://produto.mercadolivre.com.br/MLB-4004879205-meia-calca-de-l-termica-translucida-pelucia-forrada-pelinho-_JM?matt_word=birutaofertas&matt_tool=48037708",
      "categoria": "Moda",
      "img": "https://http2.mlstatic.com/D_Q_NP_2X_807585-MLB86376377902_062025-O-meia-calca-de-l-termica-translucida-pelucia-forrada-pelinho.webp",
      "emoji": "👗",
      "destaque": true
    },
    {
      "title": "Camisa Brasil Masculina Versão Retrô Comemorativa",
      "price": 96.0,
      "original_price": 249.0,
      "discount": 61,
      "permalink": "https://produto.mercadolivre.com.br/MLB-4536505969-camisa-brasil-masculina-verso-retr-comemorativa-_JM?matt_word=birutaofertas&matt_tool=48037708",
      "categoria": "Esportes",
      "img": "https://http2.mlstatic.com/D_Q_NP_2X_934469-MLB112001467261_052026-O-camisa-brasil-masculina-verso-retr-comemorativa.webp",
      "emoji": "⚽",
      "destaque": true
    },
    {
      "title": "Aparador De Pelos Super Groom 10 Mondial Bivolt Bg-03 Preto/azul 127/220v",
      "price": 89.0,
      "original_price": 227.0,
      "discount": 61,
      "permalink": "https://www.mercadolivre.com.br/aparador-de-pelos-super-groom-10-mondial-bivolt-bg-03/p/MLB44540032?matt_word=birutaofertas&matt_tool=48037708",
      "categoria": "Beleza",
      "img": "https://http2.mlstatic.com/D_Q_NP_2X_732266-MLA99394408150_112025-AB.webp",
      "emoji": "💄",
      "destaque": true
    },
    {
      "title": "Celular Samsung Galaxy A17 5g Com Ia, 128gb, 4gb Ram, Câm De 50mp, Tela De 6.7 , Nfc, Ip54 - Preto",
      "price": 758.0,
      "original_price": 1855.0,
      "discount": 59,
      "permalink": "https://www.mercadolivre.com.br/celular-samsung-galaxy-a17-5g-com-ia-128gb-4gb-ram-cm-de-50mp-tela-de-67-nfc-ip54-preto/p/MLB55027309?matt_word=birutaofertas&matt_tool=48037708",
      "categoria": "Ofertas do Dia",
      "img": "https://http2.mlstatic.com/D_Q_NP_2X_755351-MLA99597188918_122025-AB.webp",
      "emoji": "🔥",
      "destaque": true
    },
    {
      "title": "Celular Samsung Galaxy A17 5g Com Ia, 128gb, 4gb Ram, Câm De 50mp, Tela De 6.7 , Nfc, Ip54 - Cinza",
      "price": 764.0,
      "original_price": 1855.0,
      "discount": 59,
      "permalink": "https://www.mercadolivre.com.br/celular-samsung-galaxy-a17-5g-com-ia-128gb-4gb-ram-cm-de-50mp-tela-de-67-nfc-ip54-cinza/p/MLB55521828?matt_word=birutaofertas&matt_tool=48037708",
      "categoria": "Ofertas do Dia",
      "img": "https://http2.mlstatic.com/D_Q_NP_2X_873869-MLA92299394919_092025-AB.webp",
      "emoji": "🔥",
      "destaque": true
    },
    {
      "title": "Xiaomi Poco X7 Pro Dual Sim 5g 512gb Preto 12ram 50mpx",
      "price": 2327.0,
      "original_price": 5697.0,
      "discount": 59,
      "permalink": "https://www.mercadolivre.com.br/xiaomi-poco-x7-pro-dual-sim-5g-512gb-preto-12ram-50mpx/p/MLB45766004?matt_word=birutaofertas&matt_tool=48037708",
      "categoria": "Celulares",
      "img": "https://http2.mlstatic.com/D_Q_NP_2X_744110-MLA99521621748_122025-AB.webp",
      "emoji": "📱",
      "destaque": true
    },
    {
      "title": "Capa Capinha P/ Samsung Case Fosco Premium Com Magsafe",
      "price": 41.0,
      "original_price": 99.0,
      "discount": 59,
      "permalink": "https://produto.mercadolivre.com.br/MLB-3584278875-capa-capinha-p-samsung-case-fosco-premium-com-magsafe-_JM?matt_word=birutaofertas&matt_tool=48037708",
      "categoria": "Celulares",
      "img": "https://http2.mlstatic.com/D_Q_NP_2X_722915-MLB76383246381_052024-O-capa-capinha-p-samsung-case-fosco-premium-com-magsafe.webp",
      "emoji": "📱",
      "destaque": true
    },
    {
      "title": "Câmera De Segurança Wi-fi Icsee/yoosee A28b 4k Dupla Lente Visão Noturna Colorida Full Hd Externa Prova D'água Ip66 Sensor Movimento Woosh A",
      "price": 124.0,
      "original_price": 299.0,
      "discount": 59,
      "permalink": "https://www.mercadolivre.com.br/cmera-de-seguranca-wi-fi-icseeyoosee-a28b-4k-dupla-lente-viso-noturna-colorida-full-hd-externa-prova-dagua-ip66-sensor-movimento-woosh/p/MLB60074213?matt_word=birutaofertas&matt_tool=48037708",
      "categoria": "Eletrodomésticos",
      "img": "https://http2.mlstatic.com/D_Q_NP_2X_744362-MLA109507090390_042026-AB.webp",
      "emoji": "🏠",
      "destaque": true
    },
    {
      "title": "Kit 6 Cuecas Lupo Boxer Poliamida Sem Costura Box Masculina",
      "price": 129.0,
      "original_price": 316.0,
      "discount": 59,
      "permalink": "https://produto.mercadolivre.com.br/MLB-4100934467-kit-6-cuecas-lupo-boxer-poliamida-sem-costura-box-masculina-_JM?matt_word=birutaofertas&matt_tool=48037708",
      "categoria": "Moda",
      "img": "https://http2.mlstatic.com/D_Q_NP_2X_603036-MLB111121116972_052026-O-kit-6-cuecas-lupo-boxer-poliamida-sem-costura-box-masculina.webp",
      "emoji": "👗",
      "destaque": true
    },
    {
      "title": "Smart Tv Weyon 32wdsnmx 32'' Hd Led",
      "price": 721.0,
      "original_price": 1699.0,
      "discount": 58,
      "permalink": "https://www.mercadolivre.com.br/smart-tv-weyon-32wdsnmx-32-hd-led/p/MLB23537280?matt_word=birutaofertas&matt_tool=48037708",
      "categoria": "Eletrônicos",
      "img": "https://http2.mlstatic.com/D_Q_NP_2X_824259-MLA99939289013_112025-AB.webp",
      "emoji": "🔌",
      "destaque": true
    },
    {
      "title": "Transmissor Receptor Hdmi Sem Fio Wireless 1080p 50m Cinza 5v",
      "price": 254.0,
      "original_price": 599.0,
      "discount": 58,
      "permalink": "https://www.mercadolivre.com.br/transmissor-receptor-hdmi-sem-fio-wireless-1080p-50m/up/MLBU3541973031?matt_word=birutaofertas&matt_tool=48037708",
      "categoria": "Eletrônicos",
      "img": "https://http2.mlstatic.com/D_Q_NP_2X_987709-MLB98090142729_112025-AB.webp",
      "emoji": "🔌",
      "destaque": true
    },
    {
      "title": "Mochila Viagem Executiva Grande Notebook Masculina Feminina",
      "price": 104.0,
      "original_price": 249.0,
      "discount": 58,
      "permalink": "https://produto.mercadolivre.com.br/MLB-4330911507-mochila-viagem-executiva-grande-notebook-masculina-feminina-_JM?matt_word=birutaofertas&matt_tool=48037708",
      "categoria": "Moda",
      "img": "https://http2.mlstatic.com/D_Q_NP_2X_880773-MLB99691301191_112025-O-mochila-viagem-executiva-grande-notebook-masculina-feminina.webp",
      "emoji": "👗",
      "destaque": true
    },
    {
      "title": "Caminhão De Engolir Dinossauro Transformável Brinquedo 7 Em1 Dinosauros Devoram Carros Azul",
      "price": 125.0,
      "original_price": 300.0,
      "discount": 58,
      "permalink": "https://www.mercadolivre.com.br/caminhao-de-engolir-dinossauro-transformavel-brinquedo-7-em1/up/MLBU3698978967?matt_word=birutaofertas&matt_tool=48037708",
      "categoria": "Brinquedos",
      "img": "https://http2.mlstatic.com/D_Q_NP_2X_831659-MLB104477051630_012026-AB.webp",
      "emoji": "🧸",
      "destaque": true
    },
    {
      "title": "Creatina Monohidratada Pura 1kg Dark Lab Unidade Sem Sabor",
      "price": 69.0,
      "original_price": 159.0,
      "discount": 57,
      "permalink": "https://www.mercadolivre.com.br/creatina-monohidratada-pura-1kg-dark-lab-unidade-sem-sabor/p/MLB25929487?matt_word=birutaofertas&matt_tool=48037708",
      "categoria": "Ofertas do Dia",
      "img": "https://http2.mlstatic.com/D_Q_NP_2X_848860-MLA99964507641_112025-AB.webp",
      "emoji": "🔥",
      "destaque": true
    },
    {
      "title": "Tênis Masculino Casual Aramis Daily Slip Confortável Moderno",
      "price": 147.0,
      "original_price": 339.0,
      "discount": 57,
      "permalink": "https://produto.mercadolivre.com.br/MLB-4359093019-tnis-masculino-casual-aramis-daily-slip-confortavel-moderno-_JM?matt_word=birutaofertas&matt_tool=48037708",
      "categoria": "Moda",
      "img": "https://http2.mlstatic.com/D_Q_NP_2X_839947-MLB107523923436_032026-O-tnis-masculino-casual-aramis-daily-slip-confortavel-moderno.webp",
      "emoji": "👗",
      "destaque": true
    },
    {
      "title": "Tênis Fila Vector Feminino Esportivo Leve Conforto Diário",
      "price": 170.0,
      "original_price": 392.0,
      "discount": 57,
      "permalink": "https://produto.mercadolivre.com.br/MLB-4228693817-tnis-fila-vector-feminino-esportivo-leve-conforto-diario-_JM?matt_word=birutaofertas&matt_tool=48037708",
      "categoria": "Moda",
      "img": "https://http2.mlstatic.com/D_Q_NP_2X_944954-MLB93734910717_092025-O-tnis-fila-vector-feminino-esportivo-leve-conforto-diario.webp",
      "emoji": "👗",
      "destaque": true
    },
    {
      "title": "Kit 6 Cuecas Lupo Boxer Box Sem Costura Basic Microfibra",
      "price": 123.0,
      "original_price": 288.0,
      "discount": 57,
      "permalink": "https://produto.mercadolivre.com.br/MLB-1010954920-kit-6-cuecas-lupo-boxer-box-sem-costura-basic-microfibra-_JM?matt_word=birutaofertas&matt_tool=48037708",
      "categoria": "Moda",
      "img": "https://http2.mlstatic.com/D_Q_NP_2X_946503-MLB82989859698_032025-O-kit-6-cuecas-lupo-boxer-box-sem-costura-basic-microfibra.webp",
      "emoji": "👗",
      "destaque": true
    },
    {
      "title": "Smartphone Infinix Smart 10 4gb Ram 256gb Ssd Câmera 8mp + Ia, Tela 6.67 Hd+ 120hz, Bateria 5000mah, Processador T7250, Android 15 Go, Dual ",
      "price": 639.0,
      "original_price": 1458.0,
      "discount": 56,
      "permalink": "https://www.mercadolivre.com.br/smartphone-infinix-smart-10-4gb-ram-256gb-ssd-cmera-8mp-ia-tela-667-hd-120hz-bateria-5000mah-processador-t7250-android-15-go-dual-chip-preto/p/MLB56327005?matt_word=birutaofertas&matt_tool=48037708",
      "categoria": "Celulares",
      "img": "https://http2.mlstatic.com/D_Q_NP_2X_964227-MLA100071062557_122025-AB.webp",
      "emoji": "📱",
      "destaque": true
    },
    {
      "title": "Carregador Portátil Power Bank Anker 20000mah 45w Carga Turbo Rápida Display Digital Cor Preto Com 2 Cabos Usb-c Integrados, 1 Usb-c E 1 Usb",
      "price": 348.0,
      "original_price": 799.0,
      "discount": 56,
      "permalink": "https://www.mercadolivre.com.br/carregador-portatil-power-bank-anker-20000mah-45w-carga-turbo-rapida-display-digital-cor-preto-com-2-cabos-usb-c-integrados-1-usb-c-e-1-usb-a-porta-para-iphone-samsung-motorola-airpods-e-mais/p/MLB65115189?matt_word=birutaofertas&matt_tool=48037708",
      "categoria": "Celulares",
      "img": "https://http2.mlstatic.com/D_Q_NP_2X_859856-MLA105640522420_012026-AB.webp",
      "emoji": "📱",
      "destaque": true
    },
    {
      "title": "Fone De Ouvido Jskj Tws S730 Bluetooth Esportivo Preto Para Academia E Corrida",
      "price": 74.0,
      "original_price": 167.0,
      "discount": 56,
      "permalink": "https://www.mercadolivre.com.br/fone-de-ouvido-jskj-tws-s730-bluetooth-esportivo-preto-para-academia-e-corrida/p/MLB65220636?matt_word=birutaofertas&matt_tool=48037708",
      "categoria": "Celulares",
      "img": "https://http2.mlstatic.com/D_Q_NP_2X_869980-MLA106811147335_022026-AB.webp",
      "emoji": "📱",
      "destaque": true
    },
    {
      "title": "Kit 4 Camiseta Dry-fit Sandrini Masculina Academia Caminhada",
      "price": 59.0,
      "original_price": 135.0,
      "discount": 56,
      "permalink": "https://produto.mercadolivre.com.br/MLB-4592320910-kit-4-camiseta-dry-fit-sandrini-masculina-academia-caminhada-_JM?matt_word=birutaofertas&matt_tool=48037708",
      "categoria": "Esportes",
      "img": "https://http2.mlstatic.com/D_Q_NP_2X_626928-MLB82004918446_022025-O-kit-4-camiseta-dry-fit-sandrini-masculina-academia-caminhada.webp",
      "emoji": "⚽",
      "destaque": true
    },
    {
      "title": "Yves Saint Laurent Myslf Edp - Perfume Masculino 100ml Volume Da Unidade 100 Ml",
      "price": 666.0,
      "original_price": 1499.0,
      "discount": 56,
      "permalink": "https://www.mercadolivre.com.br/yves-saint-laurent-myslf-edp-perfume-masculino-100ml-volume-da-unidade-100-ml/p/MLB29084275?matt_word=birutaofertas&matt_tool=48037708",
      "categoria": "Beleza",
      "img": "https://http2.mlstatic.com/D_Q_NP_2X_912620-MLU73437663490_122023-AB.webp",
      "emoji": "💄",
      "destaque": true
    },
    {
      "title": "Kit Kemei Máquina De Corte Km-2299 E Acabamento Km-1102 Bivolt Preto 5v",
      "price": 131.0,
      "original_price": 299.0,
      "discount": 56,
      "permalink": "https://www.mercadolivre.com.br/kit-kemei-maquina-de-corte-km-2299-e-acabamento-km-1102-bivolt/p/MLB54245381?matt_word=birutaofertas&matt_tool=48037708",
      "categoria": "Beleza",
      "img": "https://http2.mlstatic.com/D_Q_NP_2X_654722-MLA100162412939_122025-AB.webp",
      "emoji": "💄",
      "destaque": true
    },
    {
      "title": "Smartphone Motorola Edge 60 Neo 5g - 256gb 24gb (12gb Ram + 12gb Ram Boost) 50mp Sony Camera Moto Ai E Tela 1.5k Super Hd - Cinza",
      "price": 1799.0,
      "original_price": 3999.0,
      "discount": 55,
      "permalink": "https://www.mercadolivre.com.br/smartphone-motorola-edge-60-neo-5g-256gb-24gb-12gb-ram-12gb-ram-boost-50mp-sony-camera-moto-ai-e-tela-15k-super-hd-cinza/p/MLB58684601?matt_word=birutaofertas&matt_tool=48037708",
      "categoria": "Ofertas do Dia",
      "img": "https://http2.mlstatic.com/D_Q_NP_2X_763543-MLA99919842737_112025-AB.webp",
      "emoji": "🔥",
      "destaque": true
    },
    {
      "title": "Celular Samsung Galaxy A17 5g Com Ia, 128gb, 4gb Ram, Câm De 50mp, Tela De 6.7 , Nfc, Ip54 - Azul",
      "price": 832.0,
      "original_price": 1855.0,
      "discount": 55,
      "permalink": "https://www.mercadolivre.com.br/celular-samsung-galaxy-a17-5g-com-ia-128gb-4gb-ram-cm-de-50mp-tela-de-67-nfc-ip54-azul/p/MLB55025202?matt_word=birutaofertas&matt_tool=48037708",
      "categoria": "Celulares",
      "img": "https://http2.mlstatic.com/D_Q_NP_2X_865110-MLA91946343251_092025-AB.webp",
      "emoji": "📱",
      "destaque": true
    },
    {
      "title": "Carregador Portátil Indução 5000mah Power Bank Anker Ultra Fino Magnético Sem Fio Qi2 Carga Rápida 15w Magsafe Para iPhone 17/16/15/14/13/12",
      "price": 377.0,
      "original_price": 829.0,
      "discount": 55,
      "permalink": "https://www.mercadolivre.com.br/carregador-portatil-induco-5000mah-power-bank-anker-ultra-fino-magnetico-sem-fio-qi2-carga-rapida-15w-magsafe-para-iphone-171615141312-samsungxiaomi-usb-c-20w-carga-rapida-compacto-cor-preto/p/MLB59004770?matt_word=birutaofertas&matt_tool=48037708",
      "categoria": "Celulares",
      "img": "https://http2.mlstatic.com/D_Q_NP_2X_701407-MLA93730236880_102025-AB.webp",
      "emoji": "📱",
      "destaque": true
    },
    {
      "title": "Copa Do Mundo Fifa 2026 Kit 100 Envelopes 700 Figurinhas Copa Do Mundo 2026 100",
      "price": 599.0,
      "original_price": 1299.0,
      "discount": 54,
      "permalink": "https://www.mercadolivre.com.br/copa-do-mundo-fifa-2026-kit-100-envelopes-700-figurinhas/up/MLBU3940349724?matt_word=birutaofertas&matt_tool=48037708",
      "categoria": "Ofertas do Dia",
      "img": "https://http2.mlstatic.com/D_Q_NP_2X_641811-MLB111349001101_052026-AB.webp",
      "emoji": "🔥",
      "destaque": true
    },
    {
      "title": "Panela De Pressão Brinox Pressure 4,2l Ø20 X 14,5 Cm Vanilla Baunilha Vanila",
      "price": 219.0,
      "original_price": 477.0,
      "discount": 54,
      "permalink": "https://www.mercadolivre.com.br/panela-de-presso-brinox-pressure-42l-20-x-145-cm-vanilla-baunilha/p/MLB22663071?matt_word=birutaofertas&matt_tool=48037708",
      "categoria": "Eletrodomésticos",
      "img": "https://http2.mlstatic.com/D_Q_NP_2X_917659-MLA112161611883_052026-AB.webp",
      "emoji": "🏠",
      "destaque": true
    },
    {
      "title": "Creatina Monohidratada Pura 120 Cápsulas Dark Lab Sem",
      "price": 32.0,
      "original_price": 69.0,
      "discount": 54,
      "permalink": "https://www.mercadolivre.com.br/creatina-monohidratada-pura-120-capsulas-dark-lab/p/MLB23181844?matt_word=birutaofertas&matt_tool=48037708",
      "categoria": "Esportes",
      "img": "https://http2.mlstatic.com/D_Q_NP_2X_781740-MLA100071017091_122025-AB.webp",
      "emoji": "⚽",
      "destaque": true
    },
    {
      "title": "Kit Álbum Capa Dura + 350 Figurinhas Brinde Lata Oficial",
      "price": 407.0,
      "original_price": 889.0,
      "discount": 54,
      "permalink": "https://www.mercadolivre.com.br/kit-album-capa-dura--350-figurinhas-brinde-lata-oficial/up/MLBU3966054386?matt_word=birutaofertas&matt_tool=48037708",
      "categoria": "Brinquedos",
      "img": "https://http2.mlstatic.com/D_Q_NP_2X_806528-MLB110614695834_052026-AB.webp",
      "emoji": "🧸",
      "destaque": true
    },
    {
      "title": "Perfume Sedutor Árabe Sabah 100ml Original Feminino",
      "price": 109.0,
      "original_price": 230.0,
      "discount": 53,
      "permalink": "https://www.mercadolivre.com.br/perfume-sedutor-arabe-sabah-100ml-original-feminino/up/MLBU3054985330?matt_word=birutaofertas&matt_tool=48037708",
      "categoria": "Ofertas do Dia",
      "img": "https://http2.mlstatic.com/D_Q_NP_2X_753960-MLB78002610612_082024-AB.webp",
      "emoji": "🔥",
      "destaque": true
    },
    {
      "title": "Tênis Fila Freestyle 2 Masculino Esportivo Leve Confortável",
      "price": 186.0,
      "original_price": 392.0,
      "discount": 53,
      "permalink": "https://produto.mercadolivre.com.br/MLB-4177720415-tnis-fila-freestyle-2-masculino-esportivo-leve-confortavel-_JM?matt_word=birutaofertas&matt_tool=48037708",
      "categoria": "Esportes",
      "img": "https://http2.mlstatic.com/D_Q_NP_2X_855193-MLB108433230449_032026-O-tnis-fila-freestyle-2-masculino-esportivo-leve-confortavel.webp",
      "emoji": "⚽",
      "destaque": true
    },
    {
      "title": "Jogo De Panelas Induçao Antiaderente Cerâmica 10 Peças Ppg Pfoa Free Baunilha",
      "price": 328.0,
      "original_price": 683.0,
      "discount": 52,
      "permalink": "https://www.mercadolivre.com.br/jogo-de-panelas-inducao-antiaderente-cermica-10-pecas-ppg-pfoa-free-baunilha/p/MLB62276296?matt_word=birutaofertas&matt_tool=48037708",
      "categoria": "Eletrodomésticos",
      "img": "https://http2.mlstatic.com/D_Q_NP_2X_896529-MLA98735006295_112025-AB.webp",
      "emoji": "🏠",
      "destaque": true
    },
    {
      "title": "Perfume Masculino Arabe Salvo Intense 100ml Original C/ Nf",
      "price": 133.0,
      "original_price": 277.0,
      "discount": 52,
      "permalink": "https://www.mercadolivre.com.br/perfume-masculino-arabe-salvo-intense-100ml-original-c-nf/up/MLBU3392665458?matt_word=birutaofertas&matt_tool=48037708",
      "categoria": "Beleza",
      "img": "https://http2.mlstatic.com/D_Q_NP_2X_674365-MLB91144003669_082025-AB.webp",
      "emoji": "💄",
      "destaque": true
    },
    {
      "title": "Mondial Erb-01 Bivolt Secadora/volumizadora Rosa 127/220v",
      "price": 145.0,
      "original_price": 299.0,
      "discount": 52,
      "permalink": "https://www.mercadolivre.com.br/escova-rotativa-ceramica-tourmaline-ion-golden-rose-erb-01-mondial/p/MLB22986751?matt_word=birutaofertas&matt_tool=48037708",
      "categoria": "Beleza",
      "img": "https://http2.mlstatic.com/D_Q_NP_2X_725803-MLA102295755099_122025-AB.webp",
      "emoji": "💄",
      "destaque": true
    },
    {
      "title": "Kit 70 Figurinhas Copa Do Mundo 2026 10 Envelopes Da Panini Copa Do Mundo 2026 10",
      "price": 67.0,
      "original_price": 140.0,
      "discount": 52,
      "permalink": "https://www.mercadolivre.com.br/kit-70-figurinhas-copa-do-mundo-2026-10-envelopes-da-panini/up/MLBU3896643809?matt_word=birutaofertas&matt_tool=48037708",
      "categoria": "Brinquedos",
      "img": "https://http2.mlstatic.com/D_Q_NP_2X_904712-MLB111294752681_052026-AB.webp",
      "emoji": "🧸",
      "destaque": true
    },
    {
      "title": "Câmera Inteligente Im7 + 3mp De Resolução Branca Intelbras Branco",
      "price": 364.0,
      "original_price": 749.0,
      "discount": 51,
      "permalink": "https://www.mercadolivre.com.br/cmera-inteligente-im7-3mp-de-resoluco-branca-intelbras/p/MLB47535705?matt_word=birutaofertas&matt_tool=48037708",
      "categoria": "Eletrodomésticos",
      "img": "https://http2.mlstatic.com/D_Q_NP_2X_892568-MLA99939109103_112025-AB.webp",
      "emoji": "🏠",
      "destaque": true
    },
    {
      "title": "Kit 10 Pote De Vidro Marmita Hermético 640ml Freezer Fitness Rishon Azul-escuro",
      "price": 97.0,
      "original_price": 199.0,
      "discount": 51,
      "permalink": "https://www.mercadolivre.com.br/kit-10-pote-de-vidro-marmita-hermetico-640ml-freezer-fitness-rishon/p/MLB63904966?matt_word=birutaofertas&matt_tool=48037708",
      "categoria": "Eletrodomésticos",
      "img": "https://http2.mlstatic.com/D_Q_NP_2X_900432-MLA113518359539_062026-AB.webp",
      "emoji": "🏠",
      "destaque": true
    },
    {
      "title": "Vaso Sanitário Monobloco Caixa Acoplada Completo Privada Cor Branco Tubrax - Vab0003",
      "price": 529.0,
      "original_price": 1084.0,
      "discount": 51,
      "permalink": "https://www.mercadolivre.com.br/vaso-sanitario-monobloco-caixa-acoplada-completo-privada-cor-branco-tubrax-vab0003/p/MLB24428758?matt_word=birutaofertas&matt_tool=48037708",
      "categoria": "Eletrodomésticos",
      "img": "https://http2.mlstatic.com/D_Q_NP_2X_746046-MLA96084254075_102025-AB.webp",
      "emoji": "🏠",
      "destaque": true
    },
    {
      "title": "Câmera Ip A8 App Icsee Infravermelho Prova D'água Externa Wifi Hd Cor Branco",
      "price": 85.0,
      "original_price": 175.0,
      "discount": 51,
      "permalink": "https://www.mercadolivre.com.br/cmera-ip-a8-app-icsee-infravermelho-prova-dagua-externa-wifi-hd-cor-branco/p/MLB25474028?matt_word=birutaofertas&matt_tool=48037708",
      "categoria": "Eletrodomésticos",
      "img": "https://http2.mlstatic.com/D_Q_NP_2X_921837-MLA99700943906_122025-AB.webp",
      "emoji": "🏠",
      "destaque": true
    },
    {
      "title": "Moto Elétrica Brinq Kids Giroflex Infantil 6v Vermelha Com Baú E Pedal Vermelho 127/220v",
      "price": 256.0,
      "original_price": 522.0,
      "discount": 51,
      "permalink": "https://www.mercadolivre.com.br/moto-eletrica-brinq-kids-giroflex-infantil-6v-vermelha-com-bau-e-pedal/p/MLB42030818?matt_word=birutaofertas&matt_tool=48037708",
      "categoria": "Brinquedos",
      "img": "https://http2.mlstatic.com/D_Q_NP_2X_650996-MLA112323793804_062026-AB.webp",
      "emoji": "🧸",
      "destaque": true
    },
    {
      "title": "Tablet Positivo Vision Tab 7 - Processador Octa-core 3gb Ram 64gb Armazenamento Tela 7 Ips Bateria 3100mah, Android 14 Go, Wi-fi - Preto",
      "price": 351.0,
      "original_price": 699.0,
      "discount": 50,
      "permalink": "https://www.mercadolivre.com.br/tablet-positivo-vision-tab-7-processador-octa-core-3gb-ram-64gb-armazenamento-tela-7-ips-bateria-3100mah-android-14-go-wi-fi-preto/p/MLB39201871?matt_word=birutaofertas&matt_tool=48037708",
      "categoria": "Ofertas do Dia",
      "img": "https://http2.mlstatic.com/D_Q_NP_2X_656533-MLA111594960631_052026-AB.webp",
      "emoji": "🔥",
      "destaque": true
    },
    {
      "title": "Creatina Monohidratada Em Pote 300g 100% Pura Dark Lab Sem Sabor",
      "price": 39.0,
      "original_price": 78.0,
      "discount": 50,
      "permalink": "https://www.mercadolivre.com.br/creatina-monohidratada-em-pote-300g-100-pura-dark-lab/p/MLB19506691?matt_word=birutaofertas&matt_tool=48037708",
      "categoria": "Ofertas do Dia",
      "img": "https://http2.mlstatic.com/D_Q_NP_2X_716663-MLA99599672360_122025-AB.webp",
      "emoji": "🔥",
      "destaque": true
    },
    {
      "title": "Tênis Masculino Feminino Kappa Park 2.0 Original",
      "price": 84.0,
      "original_price": 169.0,
      "discount": 50,
      "permalink": "https://produto.mercadolivre.com.br/MLB-4049279695-tnis-masculino-feminino-kappa-park-20-original-_JM?matt_word=birutaofertas&matt_tool=48037708",
      "categoria": "Ofertas do Dia",
      "img": "https://http2.mlstatic.com/D_Q_NP_2X_636204-MLB92283366432_092025-O-tnis-masculino-feminino-kappa-park-20-original.webp",
      "emoji": "🔥",
      "destaque": true
    },
    {
      "title": "Chuveiro Lorenzetti Loren Shower Ultra Eletrônico Branco 7500w 220v 7.5 W",
      "price": 121.0,
      "original_price": 240.0,
      "discount": 50,
      "permalink": "https://www.mercadolivre.com.br/chuveiro-lorenzetti-loren-shower-ultra-eletrnico-branco-7500w/p/MLB19590092?matt_word=birutaofertas&matt_tool=48037708",
      "categoria": "Eletrodomésticos",
      "img": "https://http2.mlstatic.com/D_Q_NP_2X_765382-MLA112359218300_062026-AB.webp",
      "emoji": "🏠",
      "destaque": true
    },
    {
      "title": "Perfume Rabane 1 Million Eau De Toilette 200 Ml Masculino",
      "price": 512.0,
      "original_price": 1028.0,
      "discount": 50,
      "permalink": "https://www.mercadolivre.com.br/perfume-rabane-1-million-eau-de-toilette-200-ml-masculino/p/MLB6072140?matt_word=birutaofertas&matt_tool=48037708",
      "categoria": "Beleza",
      "img": "https://http2.mlstatic.com/D_Q_NP_2X_702638-MLA74652687496_022024-AB.webp",
      "emoji": "💄",
      "destaque": true
    },
    {
      "title": "Kit Com 10 Envelopes 3o Lote 70 Cromos Copa Do Mundo Fifa 26",
      "price": 65.0,
      "original_price": 128.0,
      "discount": 49,
      "permalink": "https://www.mercadolivre.com.br/kit-com-10-envelopes-3o-lote-70-cromos-copa-do-mundo-fifa-26/up/MLBU3892342728?matt_word=birutaofertas&matt_tool=48037708",
      "categoria": "Ofertas do Dia",
      "img": "https://http2.mlstatic.com/D_Q_NP_2X_653831-MLB110126921171_042026-AB.webp",
      "emoji": "🔥",
      "destaque": true
    },
    {
      "title": "Carregador Portátil Power Bank Anker Nano 10000mah 30w Turbo Com Cabo Usb-c Embutido E Tela Digital Leve E Compacto Original Preto",
      "price": 278.0,
      "original_price": 541.0,
      "discount": 49,
      "permalink": "https://www.mercadolivre.com.br/carregador-portatil-power-bank-anker-nano-10000mah-30w-turbo-com-cabo-usb-c-embutido-e-tela-digital-leve-e-compacto-original-preto/p/MLB52127114?matt_word=birutaofertas&matt_tool=48037708",
      "categoria": "Celulares",
      "img": "https://http2.mlstatic.com/D_Q_NP_2X_652560-MLA106624938635_022026-AB.webp",
      "emoji": "📱",
      "destaque": true
    },
    {
      "title": "Kit Com 10 Cuecas Boxer Algodão Adulto Lupo",
      "price": 165.0,
      "original_price": 321.0,
      "discount": 49,
      "permalink": "https://produto.mercadolivre.com.br/MLB-6297586954-kit-com-10-cuecas-boxer-algodo-adulto-lupo-_JM?matt_word=birutaofertas&matt_tool=48037708",
      "categoria": "Moda",
      "img": "https://http2.mlstatic.com/D_Q_NP_2X_627952-MLB107663848125_022026-O-kit-com-10-cuecas-boxer-algodo-adulto-lupo.webp",
      "emoji": "👗",
      "destaque": true
    },
    {
      "title": "Tênis Sandrini Aero Spark Corrida Academia Caminhada Leve",
      "price": 139.0,
      "original_price": 271.0,
      "discount": 49,
      "permalink": "https://produto.mercadolivre.com.br/MLB-4340888693-tnis-sandrini-aero-spark-corrida-academia-caminhada-leve-_JM?matt_word=birutaofertas&matt_tool=48037708",
      "categoria": "Moda",
      "img": "https://http2.mlstatic.com/D_Q_NP_2X_634604-MLB109373758722_042026-O-tnis-sandrini-aero-spark-corrida-academia-caminhada-leve.webp",
      "emoji": "👗",
      "destaque": true
    },
    {
      "title": "Kit 140 Figurinhas Da Copa Do Mundo 2026 Panini 20 Envelopes Copa Do Mundo 2026 20",
      "price": 143.0,
      "original_price": 280.0,
      "discount": 49,
      "permalink": "https://www.mercadolivre.com.br/kit-140-figurinhas-da-copa-do-mundo-2026-panini-20-envelopes/up/MLBU3908024210?matt_word=birutaofertas&matt_tool=48037708",
      "categoria": "Brinquedos",
      "img": "https://http2.mlstatic.com/D_Q_NP_2X_785404-MLB110359807212_052026-AB.webp",
      "emoji": "🧸",
      "destaque": true
    },
    {
      "title": "Smartphone Samsung Galaxy A36 5g 128gb 6gb Ram Câmera Tripla De Até 50mp Selfie De 12mp Ip67 Super Amoled 6.7'' Nfc Recursos Ai Android E Se",
      "price": 1318.0,
      "original_price": 2538.0,
      "discount": 48,
      "permalink": "https://www.mercadolivre.com.br/smartphone-samsung-galaxy-a36-5g-128gb-6gb-ram-cmera-tripla-de-ate-50mp-selfie-de-12mp-ip67-super-amoled-67-nfc-recursos-ai-android-e-seguranca-snapdragon-preto/p/MLB47115842?matt_word=birutaofertas&matt_tool=48037708",
      "categoria": "Celulares",
      "img": "https://http2.mlstatic.com/D_Q_NP_2X_705075-MLA99943632917_112025-AB.webp",
      "emoji": "📱",
      "destaque": true
    },
    {
      "title": "Smart Tv Profissional 4k 50  LG Uhd 50au801 Processador 7 Ai Ger8 Super Upscaling Google Cast Alexa Integrado Controle Ai Smart Magic Webos ",
      "price": 2099.0,
      "original_price": 3999.0,
      "discount": 48,
      "permalink": "https://www.mercadolivre.com.br/smart-tv-profissional-4k-50-lg-uhd-50au801-processador-7-ai-ger8-super-upscaling-google-cast-alexa-integrado-controle-ai-smart-magic-webos-25/p/MLB61517857?matt_word=birutaofertas&matt_tool=48037708",
      "categoria": "Eletrônicos",
      "img": "https://http2.mlstatic.com/D_Q_NP_2X_731891-MLA101888831643_122025-AB.webp",
      "emoji": "🔌",
      "destaque": true
    },
    {
      "title": "Cadeira De Escritório Itália Presidente Ergonômica Couro Sintético Encosto Ajustável Com Trava E Apoio Para Pés Cor Preta Luvinco Preto",
      "price": 489.0,
      "original_price": 933.0,
      "discount": 48,
      "permalink": "https://www.mercadolivre.com.br/cadeira-de-escritorio-italia-presidente-ergonmica-couro-sintetico-encosto-ajustavel-com-trava-e-apoio-para-pes-cor-preta-luvinco/p/MLB52130256?matt_word=birutaofertas&matt_tool=48037708",
      "categoria": "Eletrodomésticos",
      "img": "https://http2.mlstatic.com/D_Q_NP_2X_629145-MLA96567996718_112025-AB.webp",
      "emoji": "🏠",
      "destaque": true
    },
    {
      "title": "Câmera De Segurança Ip Wifi A8 Full Hd Icsee Ptz 355° Com Visão Noturna Áudio Bidirecional Ip66 Monitoramento Remoto Para Celular Android E ",
      "price": 78.0,
      "original_price": 149.0,
      "discount": 48,
      "permalink": "https://www.mercadolivre.com.br/cmera-de-seguranca-ip-wifi-a8-full-hd-icsee-ptz-355-com-viso-noturna-audio-bidirecional-ip66-monitoramento-remoto-para-celular-android-e-iphone/p/MLB69327437?matt_word=birutaofertas&matt_tool=48037708",
      "categoria": "Eletrodomésticos",
      "img": "https://http2.mlstatic.com/D_Q_NP_2X_797717-MLA111994035197_052026-AB.webp",
      "emoji": "🏠",
      "destaque": true
    },
    {
      "title": "Kit Par 2 Radio Baofeng 777s Walk Talk Comunicador 16 Canais Preto 127/220v",
      "price": 85.0,
      "original_price": 159.0,
      "discount": 47,
      "permalink": "https://www.mercadolivre.com.br/kit-par-2-radio-baofeng-777s-walk-talk-comunicador-16-canais/up/MLBU1446966770?matt_word=birutaofertas&matt_tool=48037708",
      "categoria": "Celulares",
      "img": "https://http2.mlstatic.com/D_Q_NP_2X_751470-MLB88748448908_082025-AB.webp",
      "emoji": "📱",
      "destaque": true
    },
    {
      "title": "Fone De Ouvido Bluetooth 5.4 Soundcore P30i Da Anker, Cancelamento De Ruído Adaptativo, Graves Poderosos, 45h De Reprodução, Estojo 2-em-1 C",
      "price": 205.0,
      "original_price": 389.0,
      "discount": 47,
      "permalink": "https://www.mercadolivre.com.br/fone-de-ouvido-bluetooth-54-soundcore-p30i-da-anker-cancelamento-de-ruido-adaptativo-graves-poderosos-45h-de-reproduco-estojo-2-em-1-com-suporte-para-celular-ip54-fone-sem-fio-tws-preto/p/MLB38176139?matt_word=birutaofertas&matt_tool=48037708",
      "categoria": "Celulares",
      "img": "https://http2.mlstatic.com/D_Q_NP_2X_760745-MLA95700724020_102025-AB.webp",
      "emoji": "📱",
      "destaque": true
    },
    {
      "title": "Positivo Vision Tab10 T3010 4gb Ram 128gb Ssd Com Capa Teclado Octa-core 5 13mp Bateria 6000mah Tela 10.1 Hd Wifi Ac E 4g Full Lamination - ",
      "price": 784.0,
      "original_price": 1475.0,
      "discount": 47,
      "permalink": "https://www.mercadolivre.com.br/positivo-vision-tab10-t3010-4gb-ram-128gb-ssd-com-capa-teclado-octa-core-5-13mp-bateria-6000mah-tela-101-hd-wifi-ac-e-4g-full-lamination-preto/p/MLB31541424?matt_word=birutaofertas&matt_tool=48037708",
      "categoria": "Informática",
      "img": "https://http2.mlstatic.com/D_Q_NP_2X_767959-MLA112624684833_062026-AB.webp",
      "emoji": "💻",
      "destaque": true
    },
    {
      "title": "Cabo De Rede Furukawa Cat 5e Caixa 305m Cmx Soho Plus",
      "price": 799.0,
      "original_price": 1497.0,
      "discount": 47,
      "permalink": "https://www.mercadolivre.com.br/cabo-de-rede-furukawa-cat-5e-caixa-305m-cmx-soho-plus/p/MLB29010915?matt_word=birutaofertas&matt_tool=48037708",
      "categoria": "Eletrônicos",
      "img": "https://http2.mlstatic.com/D_Q_NP_2X_776482-MLA107686758412_032026-AB.webp",
      "emoji": "🔌",
      "destaque": true
    },
    {
      "title": "Kit 2 Câmera Segurança Ip Interna Externa Wifi Icsee Infravermelho Prova Dágua - Hw Branco",
      "price": 178.0,
      "original_price": 339.0,
      "discount": 47,
      "permalink": "https://www.mercadolivre.com.br/kit-2-cmera-seguranca-ip-interna-externa-wifi-icsee-infravermelho-prova-dagua-hw/p/MLB46836439?matt_word=birutaofertas&matt_tool=48037708",
      "categoria": "Eletrodomésticos",
      "img": "https://http2.mlstatic.com/D_Q_NP_2X_901090-MLA99414404486_112025-AB.webp",
      "emoji": "🏠",
      "destaque": true
    },
    {
      "title": "Câmera Segurança Ip Externa Wifi A28 App Icsee À Prova Dágua Ip66 Dome Lente Dupla Lentes 2 Em 1 Vigilancia Visão Noturna Infravermelho  4k ",
      "price": 106.0,
      "original_price": 200.0,
      "discount": 47,
      "permalink": "https://www.mercadolivre.com.br/camera-seguranca-ip-externa-wifi-a28-app-icsee-a-prova-dagua/up/MLBU3403280878?matt_word=birutaofertas&matt_tool=48037708",
      "categoria": "Eletrodomésticos",
      "img": "https://http2.mlstatic.com/D_Q_NP_2X_927792-MLB91185357960_092025-AB.webp",
      "emoji": "🏠",
      "destaque": true
    },
    {
      "title": "Vaso Sanitário Monobloco Caixa Acoplada Privada Completo Cor Branco - Vab0004",
      "price": 473.0,
      "original_price": 899.0,
      "discount": 47,
      "permalink": "https://www.mercadolivre.com.br/vaso-sanitario-monobloco-caixa-acoplada-privada-completo-cor-branco-vab0004/p/MLB24236258?matt_word=birutaofertas&matt_tool=48037708",
      "categoria": "Eletrodomésticos",
      "img": "https://http2.mlstatic.com/D_Q_NP_2X_936968-MLA95666211942_102025-AB.webp",
      "emoji": "🏠",
      "destaque": true
    },
    {
      "title": "Camisa Azul Traje Cazétv",
      "price": 85.0,
      "original_price": 159.0,
      "discount": 47,
      "permalink": "https://produto.mercadolivre.com.br/MLB-4658094775-camisa-azul-traje-cazetv-_JM?matt_word=birutaofertas&matt_tool=48037708",
      "categoria": "Moda",
      "img": "https://http2.mlstatic.com/D_Q_NP_2X_864075-MLB112336692239_052026-O-camisa-azul-traje-cazetv.webp",
      "emoji": "👗",
      "destaque": true
    },
    {
      "title": "Camisa Preta Traje Cazétv",
      "price": 85.0,
      "original_price": 159.0,
      "discount": 47,
      "permalink": "https://produto.mercadolivre.com.br/MLB-6723574982-camisa-preta-traje-cazetv-_JM?matt_word=birutaofertas&matt_tool=48037708",
      "categoria": "Moda",
      "img": "https://http2.mlstatic.com/D_Q_NP_2X_816797-MLB113158747391_062026-O-camisa-preta-traje-cazetv.webp",
      "emoji": "👗",
      "destaque": true
    },
    {
      "title": "Camisa 10 Amarela Traje  Cazétv",
      "price": 85.0,
      "original_price": 159.0,
      "discount": 47,
      "permalink": "https://produto.mercadolivre.com.br/MLB-6723882632-camisa-10-amarela-traje-cazetv-_JM?matt_word=birutaofertas&matt_tool=48037708",
      "categoria": "Esportes",
      "img": "https://http2.mlstatic.com/D_Q_NP_2X_722510-MLB112112112156_062026-O-camisa-10-amarela-traje-cazetv.webp",
      "emoji": "⚽",
      "destaque": true
    },
    {
      "title": "Smartphone Samsung Galaxy A36 5g 128gb 6gb Ram Câmera Tripla De Até 50mp Selfie De 12mp Ip67 Super Amoled 6.7'' Nfc Recursos Ai Android E Se",
      "price": 1365.0,
      "original_price": 2538.0,
      "discount": 46,
      "permalink": "https://www.mercadolivre.com.br/smartphone-samsung-galaxy-a36-5g-128gb-6gb-ram-cmera-tripla-de-ate-50mp-selfie-de-12mp-ip67-super-amoled-67-nfc-recursos-ai-android-e-seguranca-snapdragon-violeta/p/MLB47113437?matt_word=birutaofertas&matt_tool=48037708",
      "categoria": "Celulares",
      "img": "https://http2.mlstatic.com/D_Q_NP_2X_925275-MLA99995733515_112025-AB.webp",
      "emoji": "📱",
      "destaque": true
    },
    {
      "title": "Bola De Futebol Oficial Copa Do Mundo 2026 Licenciada Branco/azul/verde",
      "price": 93.0,
      "original_price": 171.0,
      "discount": 46,
      "permalink": "https://www.mercadolivre.com.br/bola-de-futebol-oficial-copa-do-mundo-2026-licenciada/up/MLBU3845169366?matt_word=birutaofertas&matt_tool=48037708",
      "categoria": "Esportes",
      "img": "https://http2.mlstatic.com/D_Q_NP_2X_773792-MLB109885988249_032026-AB.webp",
      "emoji": "⚽",
      "destaque": true
    },
    {
      "title": "Perfume Lattafa Asad 100ml Eau De Parfum Original Árabe Original Com Nota Fiscal E Selo Original Lataffa",
      "price": 156.0,
      "original_price": 289.0,
      "discount": 46,
      "permalink": "https://www.mercadolivre.com.br/perfume-lattafa-asad-100ml-eau-de-parfum-original-arabe-original-com-nota-fiscal-e-selo-original-lataffa/up/MLBU2927448939?matt_word=birutaofertas&matt_tool=48037708",
      "categoria": "Beleza",
      "img": "https://http2.mlstatic.com/D_Q_NP_2X_687418-MLB81527468562_012025-AB.webp",
      "emoji": "💄",
      "destaque": true
    },
    {
      "title": "Perfume Arabe Feminino Al Wataniah Sabah Al Ward Edp 100ml",
      "price": 110.0,
      "original_price": 199.0,
      "discount": 45,
      "permalink": "https://www.mercadolivre.com.br/perfume-arabe-feminino-al-wataniah-sabah-al-ward-edp-100ml/up/MLBU3402023514?matt_word=birutaofertas&matt_tool=48037708",
      "categoria": "Beleza",
      "img": "https://http2.mlstatic.com/D_Q_NP_2X_722022-MLB104540037760_012026-AB.webp",
      "emoji": "💄",
      "destaque": true
    },
    {
      "title": "L'oréal Professionnel Inforcer Kit Shampoo + Máscara 250ml",
      "price": 199.0,
      "original_price": 360.0,
      "discount": 45,
      "permalink": "https://www.mercadolivre.com.br/loreal-professionnel-inforcer-kit-shampoo-mascara-250ml/p/MLB29482203?matt_word=birutaofertas&matt_tool=48037708",
      "categoria": "Beleza",
      "img": "https://http2.mlstatic.com/D_Q_NP_2X_890250-MLA99419188412_112025-AB.webp",
      "emoji": "💄",
      "destaque": true
    },
    {
      "title": "Smart Tv 43 Philco P43vik Roku Led Dolby Audio Wi-fi Hdmi Hdr Full Hd 110/220v",
      "price": 1399.0,
      "original_price": 2499.0,
      "discount": 44,
      "permalink": "https://www.mercadolivre.com.br/smart-tv-43-philco-p43vik-roku-led-dolby-audio-wi-fi-hdmi-hdr-full-hd-110220v/p/MLB63040715?matt_word=birutaofertas&matt_tool=48037708",
      "categoria": "Eletrônicos",
      "img": "https://http2.mlstatic.com/D_Q_NP_2X_697288-MLA100482486016_122025-AB.webp",
      "emoji": "🔌",
      "destaque": true
    },
    {
      "title": "Smart Tv Tcl 55 Polegadas Qled 4k P8k Wifi Bluetooth Google Tv 144hz Hdr10+ Dolby Atmos Vision 55p8k",
      "price": 2754.0,
      "original_price": 4949.0,
      "discount": 44,
      "permalink": "https://www.mercadolivre.com.br/smart-tv-tcl-55-polegadas-qled-4k-p8k-wifi-bluetooth-google-tv-144hz-hdr10-dolby-atmos-vision-55p8k/p/MLB48946085?matt_word=birutaofertas&matt_tool=48037708",
      "categoria": "Eletrônicos",
      "img": "https://http2.mlstatic.com/D_Q_NP_2X_742774-MLA113356811449_062026-AB.webp",
      "emoji": "🔌",
      "destaque": true
    },
    {
      "title": "Smart Tv Samsung Ls32betblggxzd 32  Hd Led",
      "price": 1127.0,
      "original_price": 2000.0,
      "discount": 44,
      "permalink": "https://www.mercadolivre.com.br/smart-tv-samsung-ls32betblggxzd-32-hd-led/p/MLB30999973?matt_word=birutaofertas&matt_tool=48037708",
      "categoria": "Eletrônicos",
      "img": "https://http2.mlstatic.com/D_Q_NP_2X_959706-MLA99950013507_112025-AB.webp",
      "emoji": "🔌",
      "destaque": true
    },
    {
      "title": "Kit Body Splash Masculino Barbarius + Enigma + Midtown 200ml",
      "price": 79.0,
      "original_price": 140.0,
      "discount": 44,
      "permalink": "https://www.mercadolivre.com.br/kit-body-splash-masculino-barbarius-enigma-midtown-200ml/p/MLB68104527?matt_word=birutaofertas&matt_tool=48037708",
      "categoria": "Beleza",
      "img": "https://http2.mlstatic.com/D_Q_NP_2X_997574-MLA109633443994_042026-AB.webp",
      "emoji": "💄",
      "destaque": true
    },
    {
      "title": "Placa De Vídeo Nvidia Geforce Palit Rtx5060 8gb Infinity2 Oc",
      "price": 2279.0,
      "original_price": 3999.0,
      "discount": 43,
      "permalink": "https://www.mercadolivre.com.br/placa-de-video-nvidia-geforce-palit-rtx5060-8gb-infinity2-oc/p/MLB65407224?matt_word=birutaofertas&matt_tool=48037708",
      "categoria": "Informática",
      "img": "https://http2.mlstatic.com/D_Q_NP_2X_840054-MLA106181591008_022026-AB.webp",
      "emoji": "💻",
      "destaque": true
    },
    {
      "title": "Notebook Acer Aspire 5 A515-45-r2a3 Amd Ryzen 5 Windows 11 Home 8gb 512gb Ssd 15,6' Full Hd Gamut",
      "price": 3222.0,
      "original_price": 5609.0,
      "discount": 43,
      "permalink": "https://www.mercadolivre.com.br/notebook-acer-aspire-5-a515-45-r2a3-amd-ryzen-5-windows-11-home-8gb-512gb-ssd-156-full-hd/p/MLB22246671?matt_word=birutaofertas&matt_tool=48037708",
      "categoria": "Informática",
      "img": "https://http2.mlstatic.com/D_Q_NP_2X_759351-MLU77118311686_062024-AB.webp",
      "emoji": "💻",
      "destaque": true
    },
    {
      "title": "Smart Tv Philco 58 P58vik 4k Uhd Led Roku Dolby Audio Wi-fi Hdr10 110/220v",
      "price": 2299.0,
      "original_price": 3999.0,
      "discount": 43,
      "permalink": "https://www.mercadolivre.com.br/smart-tv-philco-58-p58vik-4k-uhd-led-roku-dolby-audio-wi-fi-hdr10-110220v/p/MLB67275824?matt_word=birutaofertas&matt_tool=48037708",
      "categoria": "Eletrônicos",
      "img": "https://http2.mlstatic.com/D_Q_NP_2X_668507-MLA108744768802_032026-AB.webp",
      "emoji": "🔌",
      "destaque": true
    },
    {
      "title": "Smart Tv Philco 50 P50vik 4k Uhd Led Roku Dolby Audio Wi-fi Hdr10 110/220v",
      "price": 1994.0,
      "original_price": 3499.0,
      "discount": 43,
      "permalink": "https://www.mercadolivre.com.br/smart-tv-philco-50-p50vik-4k-uhd-led-roku-dolby-audio-wi-fi-hdr10-110220v/p/MLB67267597?matt_word=birutaofertas&matt_tool=48037708",
      "categoria": "Eletrônicos",
      "img": "https://http2.mlstatic.com/D_Q_NP_2X_753324-MLA108743670040_032026-AB.webp",
      "emoji": "🔌",
      "destaque": true
    },
    {
      "title": "Projetor Smart Portátil Full Hd 4k Bluetooth Android Wifi  Branco 127/220v",
      "price": 199.0,
      "original_price": 349.0,
      "discount": 43,
      "permalink": "https://www.mercadolivre.com.br/projetor-smart-portatil-full-hd-4k-bluetooth-android-wifi/up/MLBU765509845?matt_word=birutaofertas&matt_tool=48037708",
      "categoria": "Eletrônicos",
      "img": "https://http2.mlstatic.com/D_Q_NP_2X_645947-MLB88739179054_082025-AB.webp",
      "emoji": "🔌",
      "destaque": true
    },
    {
      "title": "Smart Tv 24 Led Hd Weyon Android Tv Hdmi Usb Wifi 24wdsnbx",
      "price": 679.0,
      "original_price": 1199.0,
      "discount": 43,
      "permalink": "https://www.mercadolivre.com.br/smart-tv-24-led-hd-weyon-android-tv-hdmi-usb-wifi-24wdsnbx/p/MLB69672447?matt_word=birutaofertas&matt_tool=48037708",
      "categoria": "TV e Vídeo",
      "img": "https://http2.mlstatic.com/D_Q_NP_2X_946588-MLA111698961525_052026-AB.webp",
      "emoji": "📺",
      "destaque": true
    },
    {
      "title": "Máquina De Acabamento Corta Cabelo Profissional Kemei 2299 P Preto 127/220v",
      "price": 79.0,
      "original_price": 139.0,
      "discount": 43,
      "permalink": "https://www.mercadolivre.com.br/maquina-de-acabamento-corta-cabelo-profissional-kemei-2299-p/up/MLBU3555982525?matt_word=birutaofertas&matt_tool=48037708",
      "categoria": "Beleza",
      "img": "https://http2.mlstatic.com/D_Q_NP_2X_921106-MLB111066859744_052026-AB.webp",
      "emoji": "💄",
      "destaque": true
    },
    {
      "title": "Chapinha Profissional Mq Pro 480 Turbo Cor Black E Detalhes Silver Preto 127/220v",
      "price": 309.0,
      "original_price": 539.0,
      "discount": 43,
      "permalink": "https://www.mercadolivre.com.br/chapinha-profissional-mq-pro-480-turbo-cor-black-e-detalhes-silver/p/MLB26703117?matt_word=birutaofertas&matt_tool=48037708",
      "categoria": "Beleza",
      "img": "https://http2.mlstatic.com/D_Q_NP_2X_818498-MLA99527505846_122025-AB.webp",
      "emoji": "💄",
      "destaque": true
    },
    {
      "title": "Monitor LG Gamer 24  24ms500-b Ips Fhd 100hz Anti-reflexo Pr Preto Bivolt",
      "price": 519.0,
      "original_price": 899.0,
      "discount": 42,
      "permalink": "https://www.mercadolivre.com.br/monitor-lg-gamer-24--24ms500b-ips-fhd-100hz-antireflexo-pr/up/MLBU3013726314?matt_word=birutaofertas&matt_tool=48037708",
      "categoria": "Informática",
      "img": "https://http2.mlstatic.com/D_Q_NP_2X_871469-MLB93485352059_092025-AB.webp",
      "emoji": "💻",
      "destaque": true
    },
    {
      "title": "Smart Tv Profissional 4k 43  LG Uhd 43au801 Processador 7 Ai Ger8 Super Upscaling Google Cast Alexa Integrado Controle Ai Smart Magic Webos ",
      "price": 1737.0,
      "original_price": 2999.0,
      "discount": 42,
      "permalink": "https://www.mercadolivre.com.br/smart-tv-profissional-4k-43-lg-uhd-43au801-processador-7-ai-ger8-super-upscaling-google-cast-alexa-integrado-controle-ai-smart-magic-webos-25/p/MLB60390574?matt_word=birutaofertas&matt_tool=48037708",
      "categoria": "Eletrônicos",
      "img": "https://http2.mlstatic.com/D_Q_NP_2X_663736-MLA101387825184_122025-AB.webp",
      "emoji": "🔌",
      "destaque": true
    },
    {
      "title": "Smart Tv Samsung 43 Ls43f6000fgxzd Full Hd Led 110v/220v",
      "price": 1546.0,
      "original_price": 2665.0,
      "discount": 42,
      "permalink": "https://www.mercadolivre.com.br/smart-tv-samsung-43-ls43f6000fgxzd-full-hd-led-110v220v/p/MLB63777677?matt_word=birutaofertas&matt_tool=48037708",
      "categoria": "Eletrônicos",
      "img": "https://http2.mlstatic.com/D_Q_NP_2X_850374-MLA103344560695_012026-AB.webp",
      "emoji": "🔌",
      "destaque": true
    },
    {
      "title": "Perfume Árabe Lattafa Yara Feminino Eau De Parfum 100ml 100 Ml",
      "price": 130.0,
      "original_price": 224.0,
      "discount": 42,
      "permalink": "https://www.mercadolivre.com.br/perfume-arabe-lattafa-yara-feminino-eau-de-parfum-100ml/up/MLBU4039011825?matt_word=birutaofertas&matt_tool=48037708",
      "categoria": "Beleza",
      "img": "https://http2.mlstatic.com/D_Q_NP_2X_860185-MLB111629954252_062026-AB.webp",
      "emoji": "💄",
      "destaque": true
    },
    {
      "title": "Secador De Cabelo 2000 Watts - Style Pro Taiff Prata 127v",
      "price": 201.0,
      "original_price": 348.0,
      "discount": 42,
      "permalink": "https://www.mercadolivre.com.br/secador-de-cabelo-2000-watts-style-pro-taiff/p/MLB18572392?matt_word=birutaofertas&matt_tool=48037708",
      "categoria": "Beleza",
      "img": "https://http2.mlstatic.com/D_Q_NP_2X_889216-MLA99506441392_112025-AB.webp",
      "emoji": "💄",
      "destaque": true
    },
    {
      "title": "Kit 350 Figurinhas Copa Do Mundo 2026 50 Envelopes Da Panini Copa Do Mundo 2026 50",
      "price": 346.0,
      "original_price": 599.0,
      "discount": 42,
      "permalink": "https://www.mercadolivre.com.br/kit-350-figurinhas-copa-do-mundo-2026-50-envelopes-da-panini/up/MLBU3981471848?matt_word=birutaofertas&matt_tool=48037708",
      "categoria": "Brinquedos",
      "img": "https://http2.mlstatic.com/D_Q_NP_2X_620318-MLB111827485681_052026-AB.webp",
      "emoji": "🧸",
      "destaque": true
    },
    {
      "title": "Smart Tv De 24  Philco Roku Tv Ptv24g5yr2cp Led - Preto",
      "price": 762.0,
      "original_price": 1299.0,
      "discount": 41,
      "permalink": "https://www.mercadolivre.com.br/smart-tv-de-24-philco-roku-tv-ptv24g5yr2cp-led-preto/p/MLB38223355?matt_word=birutaofertas&matt_tool=48037708",
      "categoria": "Eletrônicos",
      "img": "https://http2.mlstatic.com/D_Q_NP_2X_702581-MLA100027792017_122025-AB.webp",
      "emoji": "🔌",
      "destaque": true
    },
    {
      "title": "Monitor Gamer LG Ultragear 24 24gs60f-b Ips Full Hd 180hz 1ms (gtg) Nvidia® G-sync® Amd Freesync Hdr10 Srgb 99% Hdmi Displayport Preto 127/2",
      "price": 779.0,
      "original_price": 1299.0,
      "discount": 40,
      "permalink": "https://www.mercadolivre.com.br/monitor-gamer-lg-ultragear-24-24gs60f-b-ips-full-hd-180hz-1ms-gtg-nvidia-g-sync-amd-freesync-hdr10-srgb-99-hdmi-displayport/p/MLB38947984?matt_word=birutaofertas&matt_tool=48037708",
      "categoria": "Informática",
      "img": "https://http2.mlstatic.com/D_Q_NP_2X_817281-MLA107167838581_022026-AB.webp",
      "emoji": "💻",
      "destaque": true
    },
    {
      "title": "Caixa De Som Boombox Plus Aiwa Bbs-01-lbl 200w Bluetooth 30h Ip66 Usb Rgb Azul 127/220v",
      "price": 1254.0,
      "original_price": 2100.0,
      "discount": 40,
      "permalink": "https://www.mercadolivre.com.br/caixa-de-som-boombox-plus-aiwa-bbs-01-lbl-200w-bluetooth-30h-ip66-usb-rgb/p/MLB38520699?matt_word=birutaofertas&matt_tool=48037708",
      "categoria": "Eletrônicos",
      "img": "https://http2.mlstatic.com/D_Q_NP_2X_727609-MLA99966959201_112025-AB.webp",
      "emoji": "🔌",
      "destaque": true
    },
    {
      "title": "Projetor 4k Ultra Hd Hy320 Smart Wi-fi 6 Bluetooth Android Cor Preto 127/220v",
      "price": 200.0,
      "original_price": 329.0,
      "discount": 39,
      "permalink": "https://www.mercadolivre.com.br/projetor-4k-ultra-hd-hy320-smart-wi-fi-6-bluetooth-android-cor-preto/p/MLB63950169?matt_word=birutaofertas&matt_tool=48037708",
      "categoria": "Informática",
      "img": "https://http2.mlstatic.com/D_Q_NP_2X_794669-MLA103476925132_012026-AB.webp",
      "emoji": "💻",
      "destaque": true
    },
    {
      "title": "Smart Tv Philips 50 4k 50pug7300 Comando De Voz Bluetooth",
      "price": 1886.0,
      "original_price": 3099.0,
      "discount": 39,
      "permalink": "https://www.mercadolivre.com.br/smart-tv-philips-50-4k-50pug7300-comando-de-voz-bluetooth/p/MLB57723340?matt_word=birutaofertas&matt_tool=48037708",
      "categoria": "TV e Vídeo",
      "img": "https://http2.mlstatic.com/D_Q_NP_2X_603690-MLA93305557455_092025-AB.webp",
      "emoji": "📺",
      "destaque": true
    },
    {
      "title": "Smart Tv Samsung 32 Ls32h5000fgxzd Hd Led Wifi Hdmi 110/220v",
      "price": 968.0,
      "original_price": 1599.0,
      "discount": 39,
      "permalink": "https://www.mercadolivre.com.br/smart-tv-samsung-32-ls32h5000fgxzd-hd-led-wifi-hdmi-110220v/p/MLB66191173?matt_word=birutaofertas&matt_tool=48037708",
      "categoria": "TV e Vídeo",
      "img": "https://http2.mlstatic.com/D_Q_NP_2X_899090-MLA107424021398_032026-AB.webp",
      "emoji": "📺",
      "destaque": true
    },
    {
      "title": "Monitor 19 Polegada Led Hd 60hz Vx190x Pc Jogo Preto",
      "price": 193.0,
      "original_price": 313.0,
      "discount": 38,
      "permalink": "https://www.mercadolivre.com.br/monitor-19-polegada-led-hd-60hz-vx190x-pc-jogo/p/MLB37987022?matt_word=birutaofertas&matt_tool=48037708",
      "categoria": "Informática",
      "img": "https://http2.mlstatic.com/D_Q_NP_2X_953382-MLA91463584936_092025-AB.webp",
      "emoji": "💻",
      "destaque": true
    },
    {
      "title": "Impressora Multifuncional Hp Deskjet Ink Advantage 2975 Colorida 1 Usb 2.0 De Alta Velocidade Wi-fi De Banda Dupla - 100 A 240 Vca - Aj4y4a#",
      "price": 445.0,
      "original_price": 719.0,
      "discount": 38,
      "permalink": "https://www.mercadolivre.com.br/impressora-multifuncional-hp-deskjet-ink-advantage-2975-colorida-1-usb-20-de-alta-velocidade-wi-fi-de-banda-dupla-100-a-240-vca-aj4y4aak4/p/MLB62998911?matt_word=birutaofertas&matt_tool=48037708",
      "categoria": "Informática",
      "img": "https://http2.mlstatic.com/D_Q_NP_2X_641445-MLA107256158981_022026-AB.webp",
      "emoji": "💻",
      "destaque": true
    },
    {
      "title": "Projetor Magcubic L018 Led Full Hd 1080p, Com Android 14 E Wi-fi 6 Branco 127/220v",
      "price": 672.0,
      "original_price": 1088.0,
      "discount": 38,
      "permalink": "https://www.mercadolivre.com.br/projetor-magcubic-l018-led-full-hd-1080p-com-android-14-e-wi-fi-6/p/MLB54233931?matt_word=birutaofertas&matt_tool=48037708",
      "categoria": "Informática",
      "img": "https://http2.mlstatic.com/D_Q_NP_2X_830342-MLA105579831850_012026-AB.webp",
      "emoji": "💻",
      "destaque": true
    },
    {
      "title": "Smart Tv Philco 40 P40vik Led Roku Dolby Audio Wi-fi Hdmi Hdr Full Hd 110/220v",
      "price": 1299.0,
      "original_price": 2099.0,
      "discount": 38,
      "permalink": "https://www.mercadolivre.com.br/smart-tv-philco-40-p40vik-led-roku-dolby-audio-wi-fi-hdmi-hdr-full-hd-110220v/p/MLB67270079?matt_word=birutaofertas&matt_tool=48037708",
      "categoria": "TV e Vídeo",
      "img": "https://http2.mlstatic.com/D_Q_NP_2X_797485-MLA109558284021_032026-AB.webp",
      "emoji": "📺",
      "destaque": true
    },
    {
      "title": "Cabo De Rede Furukawa Soho Plus Cat6 Cmx Cx 305m Cinza",
      "price": 1093.0,
      "original_price": 1746.0,
      "discount": 37,
      "permalink": "https://www.mercadolivre.com.br/cabo-de-rede-furukawa-soho-plus-cat6-cmx-cx-305m-cinza/p/MLB30660677?matt_word=birutaofertas&matt_tool=48037708",
      "categoria": "Informática",
      "img": "https://http2.mlstatic.com/D_Q_NP_2X_852868-MLA99950108751_112025-AB.webp",
      "emoji": "💻",
      "destaque": true
    },
    {
      "title": "Kit 4 Refil Tintas Corante Eps T544 Amarelo Ciano Magenta Preto Epson L3110 L3250",
      "price": 179.0,
      "original_price": 285.0,
      "discount": 37,
      "permalink": "https://www.mercadolivre.com.br/kit-4-refil-tintas-corante-eps-t544-amarelo-ciano-magenta-preto-epson-l3110-l3250/p/MLB51896124?matt_word=birutaofertas&matt_tool=48037708",
      "categoria": "Informática",
      "img": "https://http2.mlstatic.com/D_Q_NP_2X_984706-MLA99851664589_112025-AB.webp",
      "emoji": "💻",
      "destaque": true
    },
    {
      "title": "Smart Tv 32 Philco P32vik Roku Led Dolby Audio Hdr Wi-fi 110/220v",
      "price": 949.0,
      "original_price": 1499.0,
      "discount": 37,
      "permalink": "https://www.mercadolivre.com.br/smart-tv-32-philco-p32vik-roku-led-dolby-audio-hdr-wi-fi-110220v/p/MLB63036814?matt_word=birutaofertas&matt_tool=48037708",
      "categoria": "TV e Vídeo",
      "img": "https://http2.mlstatic.com/D_Q_NP_2X_691057-MLA100479527690_122025-AB.webp",
      "emoji": "📺",
      "destaque": true
    },
    {
      "title": "Kit 700 Figurinha Do Álbum Copa Do Mundo 2026- 100 Envelopes",
      "price": 630.0,
      "original_price": 1000.0,
      "discount": 37,
      "permalink": "https://www.mercadolivre.com.br/kit-700-figurinha-do-album-copa-do-mundo-2026-100-envelopes/up/MLBU3911772235?matt_word=birutaofertas&matt_tool=48037708",
      "categoria": "Livros",
      "img": "https://http2.mlstatic.com/D_Q_NP_2X_719889-MLB110799756479_042026-AB.webp",
      "emoji": "📚",
      "destaque": true
    },
    {
      "title": "Notebook Acer Aspire Go 15 I5-13420h, Ram 8gb, Ssd 256gb, 15,6  Full Hd, Linux  Ag15-71p-54j6 Cinza",
      "price": 3374.0,
      "original_price": 5284.0,
      "discount": 36,
      "permalink": "https://www.mercadolivre.com.br/notebook-acer-aspire-go-15-i5-13420h-ram-8gb-ssd-256gb-156-full-hd-linux-ag15-71p-54j6/p/MLB67084809?matt_word=birutaofertas&matt_tool=48037708",
      "categoria": "Informática",
      "img": "https://http2.mlstatic.com/D_Q_NP_2X_846715-MLA109375570233_032026-AB.webp",
      "emoji": "💻",
      "destaque": true
    },
    {
      "title": "Kit 168 Figurinhas Do Álbum Copa Do Mundo 2026- 24 Envelopes",
      "price": 162.0,
      "original_price": 250.0,
      "discount": 35,
      "permalink": "https://www.mercadolivre.com.br/kit-168-figurinhas-do-album-copa-do-mundo-2026-24-envelopes/up/MLBU4043324340?matt_word=birutaofertas&matt_tool=48037708",
      "categoria": "Livros",
      "img": "https://http2.mlstatic.com/D_Q_NP_2X_794739-MLB111518650952_062026-AB.webp",
      "emoji": "📚",
      "destaque": true
    },
    {
      "title": "Kit 70 Figurinhas Do Álbum Copa Do Mundo 2026 Pronta Entrega",
      "price": 67.0,
      "original_price": 100.0,
      "discount": 33,
      "permalink": "https://www.mercadolivre.com.br/kit-70-figurinhas-do-album-copa-do-mundo-2026-pronta-entrega/up/MLBU3923294598?matt_word=birutaofertas&matt_tool=48037708",
      "categoria": "Livros",
      "img": "https://http2.mlstatic.com/D_Q_NP_2X_876614-MLB110800889269_042026-AB.webp",
      "emoji": "📚",
      "destaque": true
    },
    {
      "title": "Kit 280 Figurinhas Do Álbum Copa Do Mundo 2026- 40 Envelopes",
      "price": 271.0,
      "original_price": 400.0,
      "discount": 32,
      "permalink": "https://www.mercadolivre.com.br/kit-280-figurinhas-do-album-copa-do-mundo-2026-40-envelopes/up/MLBU3911738233?matt_word=birutaofertas&matt_tool=48037708",
      "categoria": "Livros",
      "img": "https://http2.mlstatic.com/D_Q_NP_2X_833274-MLB110799343465_042026-AB.webp",
      "emoji": "📚",
      "destaque": true
    },
    {
      "title": "Kit 350 Figurinhas Do Álbum Copa Do Mundo 2026- 50 Envelopes",
      "price": 339.0,
      "original_price": 500.0,
      "discount": 32,
      "permalink": "https://www.mercadolivre.com.br/kit-350-figurinhas-do-album-copa-do-mundo-2026-50-envelopes/up/MLBU3923327842?matt_word=birutaofertas&matt_tool=48037708",
      "categoria": "Livros",
      "img": "https://http2.mlstatic.com/D_Q_NP_2X_838705-MLB110800739527_042026-AB.webp",
      "emoji": "📚",
      "destaque": true
    },
    {
      "title": "Kit 210 Figurinhas Do Álbum Copa Do Mundo 2026- 30 Envelopes",
      "price": 203.0,
      "original_price": 300.0,
      "discount": 32,
      "permalink": "https://www.mercadolivre.com.br/kit-210-figurinhas-do-album-copa-do-mundo-2026-30-envelopes/up/MLBU3911729687?matt_word=birutaofertas&matt_tool=48037708",
      "categoria": "Livros",
      "img": "https://http2.mlstatic.com/D_Q_NP_2X_738443-MLB110799846021_042026-AB.webp",
      "emoji": "📚",
      "destaque": true
    },
    {
      "title": "Livro Vencendo A Ansiedade Com Deus Pai | 40 Dias De Descanso E Confiança No Amor De Deus | Devocional Cristão | Leitura Bíblica Diária | Ch",
      "price": 19.0,
      "original_price": 59.0,
      "discount": 68,
      "permalink": "https://www.mercadolivre.com.br/livro-vencendo-a-ansiedade-com-deus-pai--40-dias-de-descanso-e-confianca-no-amor-de-deus--devocional-cristao--leitura-biblica-diaria--charles-spurgeon--penkal-books/up/MLBU1769623216?matt_word=birutaofertas&matt_tool=48037708",
      "categoria": "Livros",
      "img": "https://http2.mlstatic.com/D_Q_NP_2X_675128-MLB109856211226_042026-AB.webp",
      "emoji": "📚",
      "destaque": false
    },
    {
      "title": "Jogo Bíblico De Cartas | Onde Estou?- Penkal, De Penkal., Vol. 1. Editorial Editora Penkal Books, Capa Mole Em Português, 2025",
      "price": 22.0,
      "original_price": 59.0,
      "discount": 63,
      "permalink": "https://www.mercadolivre.com.br/jogo-biblico-de-cartas-onde-estou-penkal-de-penkal-vol-1-editorial-editora-penkal-books-capa-mole-em-portugus-2025/p/MLB54122369?matt_word=birutaofertas&matt_tool=48037708",
      "categoria": "Livros",
      "img": "https://http2.mlstatic.com/D_Q_NP_2X_770856-MLA93048531136_092025-AB.webp",
      "emoji": "📚",
      "destaque": false
    },
    {
      "title": "Jogo Bíblico De Cartas | Bíblimimícas - Penkal, De Penkal, Vol. 1. Editora Editora Penkal Books, Capa Mole (2025)",
      "price": 23.0,
      "original_price": 59.0,
      "discount": 61,
      "permalink": "https://www.mercadolivre.com.br/jogo-biblico-de-cartas-biblimimicas-penkal-de-penkal-vol-1-editora-editora-penkal-books-capa-mole-2025/p/MLB55928733?matt_word=birutaofertas&matt_tool=48037708",
      "categoria": "Livros",
      "img": "https://http2.mlstatic.com/D_Q_NP_2X_868808-MLA110985977063_042026-AB.webp",
      "emoji": "📚",
      "destaque": false
    },
    {
      "title": "Livro Histórias Bíblicas Para Hora De Dormir | Editora Penkal, De Penkal. Editora Editora Penkal Books, Capa Mole (2025)",
      "price": 24.0,
      "original_price": 59.0,
      "discount": 59,
      "permalink": "https://www.mercadolivre.com.br/livro-historias-biblicas-para-hora-de-dormir-editora-penkal-de-penkal-editora-editora-penkal-books-capa-mole-2025/p/MLB60548313?matt_word=birutaofertas&matt_tool=48037708",
      "categoria": "Livros",
      "img": "https://http2.mlstatic.com/D_Q_NP_2X_793873-MLA95196900972_102025-AB.webp",
      "emoji": "📚",
      "destaque": false
    },
    {
      "title": "70 Figurinhas 10 Pacotes Álbum Copa Do Mundo 2026 Sticker",
      "price": 70.0,
      "original_price": 166.0,
      "discount": 58,
      "permalink": "https://www.mercadolivre.com.br/70-figurinhas-10-pacotes-album-copa-do-mundo-2026-sticker/up/MLBU4043057127?matt_word=birutaofertas&matt_tool=48037708",
      "categoria": "Livros",
      "img": "https://http2.mlstatic.com/D_Q_NP_2X_709447-MLB112767359107_062026-AB.webp",
      "emoji": "📚",
      "destaque": false
    },
    {
      "title": "Coleção Como Eu Me Sinto - Livros Com Valores Familiares, Educação Emocional Infantil, Educação Positiva, Leitura De Fácil Compreensão Ricam",
      "price": 59.0,
      "original_price": 139.0,
      "discount": 58,
      "permalink": "https://www.mercadolivre.com.br/colecao-como-eu-me-sinto--livros-com-valores-familiares-educacao-emocional-infantil-educacao-positiva-leitura-de-facil-compreensao-ricamente-ilustrativo-cores-vibrantes/up/MLBU1747837341?matt_word=birutaofertas&matt_tool=48037708",
      "categoria": "Livros",
      "img": "https://http2.mlstatic.com/D_Q_NP_2X_608217-MLB93818823917_092025-AB.webp",
      "emoji": "📚",
      "destaque": false
    },
    {
      "title": "70 Figurinhas 10 Pacotes Álbum Copa Do Mundo 2026 Atualizado",
      "price": 73.0,
      "original_price": 166.0,
      "discount": 56,
      "permalink": "https://www.mercadolivre.com.br/70-figurinhas-10-pacotes-album-copa-do-mundo-2026-atualizado/up/MLBU4043010669?matt_word=birutaofertas&matt_tool=48037708",
      "categoria": "Livros",
      "img": "https://http2.mlstatic.com/D_Q_NP_2X_747192-MLB112765657469_062026-AB.webp",
      "emoji": "📚",
      "destaque": false
    },
    {
      "title": "Álbum Capa Dura Ouro Copa Do Mundo 2026 + 70 Figurinhas Full",
      "price": 174.0,
      "original_price": 399.0,
      "discount": 56,
      "permalink": "https://www.mercadolivre.com.br/album-capa-dura-ouro-copa-do-mundo-2026--70-figurinhas-full/up/MLBU4017414433?matt_word=birutaofertas&matt_tool=48037708",
      "categoria": "Livros",
      "img": "https://http2.mlstatic.com/D_Q_NP_2X_682300-MLB112404224367_052026-AB.webp",
      "emoji": "📚",
      "destaque": false
    },
    {
      "title": "Copa Do Mundo 2026 - Kit 70 Figurinhas Cromos Oficial Album",
      "price": 64.0,
      "original_price": 139.0,
      "discount": 54,
      "permalink": "https://www.mercadolivre.com.br/copa-do-mundo-2026--kit-70-figurinhas-cromos-oficial-album/up/MLBU3927644257?matt_word=birutaofertas&matt_tool=48037708",
      "categoria": "Livros",
      "img": "https://http2.mlstatic.com/D_Q_NP_2X_920231-MLB110953857938_052026-AB.webp",
      "emoji": "📚",
      "destaque": false
    }
  ]
}